COPYING
COPYING.LESSER
ChangeLog
MANIFEST.in
README
setup.py
./__init__.py
./__pkginfo__.py
./distributors.py
./fd.py
./fi.py
./interfaces.py
./propagation.py
./psyco_wrapper.py
./test/__profile__.py
./test/runtests.py
./test/test_constraints.py
./test/test_distributors.py
./test/test_domains.py
./test/test_fi.py
./test/test_propagation.py
./test/test_validation.py
constraint.egg-info/PKG-INFO
constraint.egg-info/SOURCES.txt
constraint.egg-info/dependency_links.txt
constraint.egg-info/namespace_packages.txt
constraint.egg-info/top_level.txt
doc/CONTRIBUTORS
doc/documentation.html
doc/documentation.xml
examples/chess.py
examples/conferences.py
examples/intervals.py
examples/knights.py
examples/menza.py
examples/menza2.py
examples/menza_brute_force.py
examples/money.py
examples/money2.py
examples/queens.py
examples/queens2.py
examples/queens3.py
examples/rooks.py
examples/sudoku.py
test/test_constraints.py
test/test_distributors.py
test/test_domains.py
test/test_fi.py
test/test_propagation.py
test/test_validation.py