Metadata-Version: 1.0
Name: constraint
Version: 0.4.1
Summary: constraints satisfaction solver in Python
Home-page: http://www.logilab.org/projects/constraint
Author: Alexandre Fayolle
Author-email: alexandre.fayolle@logilab.fr
License: LGPL
Platform: UNKNOWN
